{
  "pessoas": [
    {
      "id": 1,
      "nome": "Daniel Souza",
      "idade": 28,
      "cidade": "Salvador",
      "email": "daniel@example.com",
      "profissao": "Desenvolvedor"
    },
    {
      "id": 2,
      "nome": "Ana Clara Rodrigues",
      "idade": 25,
      "cidade": "São Paulo",
      "email": "ana@example.com",
      "profissao": "Designer"
    },
    {
      "id": 3,
      "nome": "Bruno Machado Lima",
      "idade": 32,
      "cidade": "Porto Alegre",
      "email": "bruno@example.com",
      "profissao": "Engenheiro"
    },
    {
      "id": 4,
      "nome": "Fernanda Souza",
      "idade": 29,
      "cidade": "Curitiba",
      "email": "fernanda@example.com",
      "profissao": "Professora"
    }
  ]
}
